ppxxh/__init__.py
ppxxh/_top.py
ppxxh/_xxh32.py
ppxxh/_xxh3_128.py
ppxxh/_xxh3_64.py
ppxxh/_xxh64.py
ppxxh-1.0.0.dist-info/LICENSE
ppxxh-1.0.0.dist-info/METADATA
ppxxh-1.0.0.dist-info/WHEEL
ppxxh-1.0.0.dist-info/top_level.txt
ppxxh-1.0.0.dist-info/RECORD
