Metadata-Version: 2.1
Name: ppxxh
Version: 1.0.0
Summary: Pure python implementation xxhash algorithms
Home-page: https://github.com/vgbundo/ppxxh
Author: Vgbundo
Author-email: vgbundo@disroot.org
License: UNKNOWN
Keywords: pure python,hash,xxh,xxhash,xxh32,xxh64,xxh3_64,xxh3_128,secret generator
Platform: UNKNOWN
Classifier: Development Status :: 5 - Production/Stable
Classifier: Intended Audience :: Developers
Classifier: License :: OSI Approved :: MIT License
Classifier: Operating System :: OS Independent
Classifier: Programming Language :: Python :: 3
Classifier: Programming Language :: Python :: 3 :: Only
Classifier: Programming Language :: Python :: 3.0
Classifier: Programming Language :: Python :: 3.1
Classifier: Programming Language :: Python :: 3.2
Classifier: Programming Language :: Python :: 3.3
Classifier: Programming Language :: Python :: 3.4
Classifier: Programming Language :: Python :: 3.5
Classifier: Programming Language :: Python :: 3.6
Classifier: Programming Language :: Python :: 3.7
Classifier: Programming Language :: Python :: 3.8
Classifier: Programming Language :: Python :: 3.9
Classifier: Programming Language :: Python :: 3.10
Classifier: Topic :: Utilities
Requires-Python: >=3.0
License-File: LICENSE
